{"nodes": [{"id": "d_code_retailer_server_src_routes_backup_routes_js", "label": "backup.routes.js", "file_type": "code", "source_file": "D:\\code\\retailer\\server\\src\\routes\\backup.routes.js", "source_location": "L1"}, {"id": "routes_backup_routes_express", "label": "express", "file_type": "code", "source_file": "D:\\code\\retailer\\server\\src\\routes\\backup.routes.js", "source_location": "L1"}, {"id": "routes_backup_routes_fs", "label": "fs", "file_type": "code", "source_file": "D:\\code\\retailer\\server\\src\\routes\\backup.routes.js", "source_location": "L2"}, {"id": "routes_backup_routes_path", "label": "path", "file_type": "code", "source_file": "D:\\code\\retailer\\server\\src\\routes\\backup.routes.js", "source_location": "L3"}, {"id": "routes_backup_routes_multer", "label": "multer", "file_type": "code", "source_file": "D:\\code\\retailer\\server\\src\\routes\\backup.routes.js", "source_location": "L4"}, {"id": "routes_backup_routes_closedb_getdb_getdbpath_initdb", "label": "{ closeDb, getDb, getDbPath, initDb }", "file_type": "code", "source_file": "D:\\code\\retailer\\server\\src\\routes\\backup.routes.js", "source_location": "L5"}, {"id": "routes_backup_routes_performbackup_islikelysqlitefile", "label": "{ performBackup, isLikelySqliteFile }", "file_type": "code", "source_file": "D:\\code\\retailer\\server\\src\\routes\\backup.routes.js", "source_location": "L6"}, {"id": "routes_backup_routes_authrequired_requirerole", "label": "{ authRequired, requireRole }", "file_type": "code", "source_file": "D:\\code\\retailer\\server\\src\\routes\\backup.routes.js", "source_location": "L7"}, {"id": "routes_backup_routes_router", "label": "router", "file_type": "code", "source_file": "D:\\code\\retailer\\server\\src\\routes\\backup.routes.js", "source_location": "L9"}, {"id": "routes_backup_routes_upload", "label": "upload", "file_type": "code", "source_file": "D:\\code\\retailer\\server\\src\\routes\\backup.routes.js", "source_location": "L10"}, {"id": "routes_backup_routes_dest", "label": "dest", "file_type": "code", "source_file": "D:\\code\\retailer\\server\\src\\routes\\backup.routes.js", "source_location": "L15"}, {"id": "routes_backup_routes_dbpath", "label": "dbPath", "file_type": "code", "source_file": "D:\\code\\retailer\\server\\src\\routes\\backup.routes.js", "source_location": "L32"}, {"id": "routes_backup_routes_rollbackbackup", "label": "rollbackBackup", "file_type": "code", "source_file": "D:\\code\\retailer\\server\\src\\routes\\backup.routes.js", "source_location": "L33"}, {"id": "routes_backup_routes_settings", "label": "settings", "file_type": "code", "source_file": "D:\\code\\retailer\\server\\src\\routes\\backup.routes.js", "source_location": "L65"}], "edges": [{"source": "d_code_retailer_server_src_routes_backup_routes_js", "target": "express", "relation": "imports_from", "context": "import", "confidence": "EXTRACTED", "source_file": "D:\\code\\retailer\\server\\src\\routes\\backup.routes.js", "source_location": "L1", "weight": 1.0}, {"source": "d_code_retailer_server_src_routes_backup_routes_js", "target": "routes_backup_routes_express", "relation": "contains", "confidence": "EXTRACTED", "source_file": "D:\\code\\retailer\\server\\src\\routes\\backup.routes.js", "source_location": "L1", "weight": 1.0}, {"source": "d_code_retailer_server_src_routes_backup_routes_js", "target": "fs", "relation": "imports_from", "context": "import", "confidence": "EXTRACTED", "source_file": "D:\\code\\retailer\\server\\src\\routes\\backup.routes.js", "source_location": "L2", "weight": 1.0}, {"source": "d_code_retailer_server_src_routes_backup_routes_js", "target": "routes_backup_routes_fs", "relation": "contains", "confidence": "EXTRACTED", "source_file": "D:\\code\\retailer\\server\\src\\routes\\backup.routes.js", "source_location": "L2", "weight": 1.0}, {"source": "d_code_retailer_server_src_routes_backup_routes_js", "target": "path", "relation": "imports_from", "context": "import", "confidence": "EXTRACTED", "source_file": "D:\\code\\retailer\\server\\src\\routes\\backup.routes.js", "source_location": "L3", "weight": 1.0}, {"source": "d_code_retailer_server_src_routes_backup_routes_js", "target": "routes_backup_routes_path", "relation": "contains", "confidence": "EXTRACTED", "source_file": "D:\\code\\retailer\\server\\src\\routes\\backup.routes.js", "source_location": "L3", "weight": 1.0}, {"source": "d_code_retailer_server_src_routes_backup_routes_js", "target": "multer", "relation": "imports_from", "context": "import", "confidence": "EXTRACTED", "source_file": "D:\\code\\retailer\\server\\src\\routes\\backup.routes.js", "source_location": "L4", "weight": 1.0}, {"source": "d_code_retailer_server_src_routes_backup_routes_js", "target": "routes_backup_routes_multer", "relation": "contains", "confidence": "EXTRACTED", "source_file": "D:\\code\\retailer\\server\\src\\routes\\backup.routes.js", "source_location": "L4", "weight": 1.0}, {"source": "d_code_retailer_server_src_routes_backup_routes_js", "target": "d_code_retailer_server_src_config_database_js", "relation": "imports_from", "context": "import", "confidence": "EXTRACTED", "source_file": "D:\\code\\retailer\\server\\src\\routes\\backup.routes.js", "source_location": "L5", "weight": 1.0}, {"source": "d_code_retailer_server_src_routes_backup_routes_js", "target": "config_database_closedb", "relation": "imports", "context": "import", "confidence": "EXTRACTED", "source_file": "D:\\code\\retailer\\server\\src\\routes\\backup.routes.js", "source_location": "L5", "weight": 1.0}, {"source": "d_code_retailer_server_src_routes_backup_routes_js", "target": "config_database_getdb", "relation": "imports", "context": "import", "confidence": "EXTRACTED", "source_file": "D:\\code\\retailer\\server\\src\\routes\\backup.routes.js", "source_location": "L5", "weight": 1.0}, {"source": "d_code_retailer_server_src_routes_backup_routes_js", "target": "config_database_getdbpath", "relation": "imports", "context": "import", "confidence": "EXTRACTED", "source_file": "D:\\code\\retailer\\server\\src\\routes\\backup.routes.js", "source_location": "L5", "weight": 1.0}, {"source": "d_code_retailer_server_src_routes_backup_routes_js", "target": "config_database_initdb", "relation": "imports", "context": "import", "confidence": "EXTRACTED", "source_file": "D:\\code\\retailer\\server\\src\\routes\\backup.routes.js", "source_location": "L5", "weight": 1.0}, {"source": "d_code_retailer_server_src_routes_backup_routes_js", "target": "routes_backup_routes_closedb_getdb_getdbpath_initdb", "relation": "contains", "confidence": "EXTRACTED", "source_file": "D:\\code\\retailer\\server\\src\\routes\\backup.routes.js", "source_location": "L5", "weight": 1.0}, {"source": "d_code_retailer_server_src_routes_backup_routes_js", "target": "d_code_retailer_server_src_services_backupservice_js", "relation": "imports_from", "context": "import", "confidence": "EXTRACTED", "source_file": "D:\\code\\retailer\\server\\src\\routes\\backup.routes.js", "source_location": "L6", "weight": 1.0}, {"source": "d_code_retailer_server_src_routes_backup_routes_js", "target": "services_backupservice_performbackup", "relation": "imports", "context": "import", "confidence": "EXTRACTED", "source_file": "D:\\code\\retailer\\server\\src\\routes\\backup.routes.js", "source_location": "L6", "weight": 1.0}, {"source": "d_code_retailer_server_src_routes_backup_routes_js", "target": "services_backupservice_islikelysqlitefile", "relation": "imports", "context": "import", "confidence": "EXTRACTED", "source_file": "D:\\code\\retailer\\server\\src\\routes\\backup.routes.js", "source_location": "L6", "weight": 1.0}, {"source": "d_code_retailer_server_src_routes_backup_routes_js", "target": "routes_backup_routes_performbackup_islikelysqlitefile", "relation": "contains", "confidence": "EXTRACTED", "source_file": "D:\\code\\retailer\\server\\src\\routes\\backup.routes.js", "source_location": "L6", "weight": 1.0}, {"source": "d_code_retailer_server_src_routes_backup_routes_js", "target": "d_code_retailer_server_src_middleware_auth_js", "relation": "imports_from", "context": "import", "confidence": "EXTRACTED", "source_file": "D:\\code\\retailer\\server\\src\\routes\\backup.routes.js", "source_location": "L7", "weight": 1.0}, {"source": "d_code_retailer_server_src_routes_backup_routes_js", "target": "middleware_auth_authrequired", "relation": "imports", "context": "import", "confidence": "EXTRACTED", "source_file": "D:\\code\\retailer\\server\\src\\routes\\backup.routes.js", "source_location": "L7", "weight": 1.0}, {"source": "d_code_retailer_server_src_routes_backup_routes_js", "target": "middleware_auth_requirerole", "relation": "imports", "context": "import", "confidence": "EXTRACTED", "source_file": "D:\\code\\retailer\\server\\src\\routes\\backup.routes.js", "source_location": "L7", "weight": 1.0}, {"source": "d_code_retailer_server_src_routes_backup_routes_js", "target": "routes_backup_routes_authrequired_requirerole", "relation": "contains", "confidence": "EXTRACTED", "source_file": "D:\\code\\retailer\\server\\src\\routes\\backup.routes.js", "source_location": "L7", "weight": 1.0}, {"source": "d_code_retailer_server_src_routes_backup_routes_js", "target": "routes_backup_routes_router", "relation": "contains", "confidence": "EXTRACTED", "source_file": "D:\\code\\retailer\\server\\src\\routes\\backup.routes.js", "source_location": "L9", "weight": 1.0}, {"source": "d_code_retailer_server_src_routes_backup_routes_js", "target": "routes_backup_routes_upload", "relation": "contains", "confidence": "EXTRACTED", "source_file": "D:\\code\\retailer\\server\\src\\routes\\backup.routes.js", "source_location": "L10", "weight": 1.0}, {"source": "d_code_retailer_server_src_routes_backup_routes_js", "target": "routes_backup_routes_dest", "relation": "contains", "confidence": "EXTRACTED", "source_file": "D:\\code\\retailer\\server\\src\\routes\\backup.routes.js", "source_location": "L15", "weight": 1.0}, {"source": "d_code_retailer_server_src_routes_backup_routes_js", "target": "routes_backup_routes_dbpath", "relation": "contains", "confidence": "EXTRACTED", "source_file": "D:\\code\\retailer\\server\\src\\routes\\backup.routes.js", "source_location": "L32", "weight": 1.0}, {"source": "d_code_retailer_server_src_routes_backup_routes_js", "target": "routes_backup_routes_rollbackbackup", "relation": "contains", "confidence": "EXTRACTED", "source_file": "D:\\code\\retailer\\server\\src\\routes\\backup.routes.js", "source_location": "L33", "weight": 1.0}, {"source": "d_code_retailer_server_src_routes_backup_routes_js", "target": "routes_backup_routes_settings", "relation": "contains", "confidence": "EXTRACTED", "source_file": "D:\\code\\retailer\\server\\src\\routes\\backup.routes.js", "source_location": "L65", "weight": 1.0}, {"source": "d_code_retailer_server_src_routes_backup_routes_js", "target": "routes_backup_routes_settings", "relation": "contains", "confidence": "EXTRACTED", "source_file": "D:\\code\\retailer\\server\\src\\routes\\backup.routes.js", "source_location": "L80", "weight": 1.0}], "raw_calls": []}