{"nodes": [{"id": "d_code_retailer_client_src_components_ui_a4pageview_jsx", "label": "A4PageView.jsx", "file_type": "code", "source_file": "D:\\code\\retailer\\client\\src\\components\\ui\\A4PageView.jsx", "source_location": "L1"}, {"id": "ui_a4pageview_fmtdateeg", "label": "fmtDateEG()", "file_type": "code", "source_file": "D:\\code\\retailer\\client\\src\\components\\ui\\A4PageView.jsx", "source_location": "L3"}, {"id": "ui_a4pageview_isnumericlike", "label": "isNumericLike()", "file_type": "code", "source_file": "D:\\code\\retailer\\client\\src\\components\\ui\\A4PageView.jsx", "source_location": "L10"}, {"id": "ui_a4pageview_a4sheet", "label": "A4Sheet()", "file_type": "code", "source_file": "D:\\code\\retailer\\client\\src\\components\\ui\\A4PageView.jsx", "source_location": "L27"}, {"id": "ui_a4pageview_usecontainerscale", "label": "useContainerScale()", "file_type": "code", "source_file": "D:\\code\\retailer\\client\\src\\components\\ui\\A4PageView.jsx", "source_location": "L261"}, {"id": "ui_a4pageview_a4pageview", "label": "A4PageView()", "file_type": "code", "source_file": "D:\\code\\retailer\\client\\src\\components\\ui\\A4PageView.jsx", "source_location": "L277"}], "edges": [{"source": "d_code_retailer_client_src_components_ui_a4pageview_jsx", "target": "react", "relation": "imports_from", "context": "import", "confidence": "EXTRACTED", "source_file": "D:\\code\\retailer\\client\\src\\components\\ui\\A4PageView.jsx", "source_location": "L1", "weight": 1.0}, {"source": "d_code_retailer_client_src_components_ui_a4pageview_jsx", "target": "ui_a4pageview_fmtdateeg", "relation": "contains", "confidence": "EXTRACTED", "source_file": "D:\\code\\retailer\\client\\src\\components\\ui\\A4PageView.jsx", "source_location": "L3", "weight": 1.0}, {"source": "d_code_retailer_client_src_components_ui_a4pageview_jsx", "target": "ui_a4pageview_isnumericlike", "relation": "contains", "confidence": "EXTRACTED", "source_file": "D:\\code\\retailer\\client\\src\\components\\ui\\A4PageView.jsx", "source_location": "L10", "weight": 1.0}, {"source": "d_code_retailer_client_src_components_ui_a4pageview_jsx", "target": "ui_a4pageview_a4sheet", "relation": "contains", "confidence": "EXTRACTED", "source_file": "D:\\code\\retailer\\client\\src\\components\\ui\\A4PageView.jsx", "source_location": "L27", "weight": 1.0}, {"source": "d_code_retailer_client_src_components_ui_a4pageview_jsx", "target": "ui_a4pageview_usecontainerscale", "relation": "contains", "confidence": "EXTRACTED", "source_file": "D:\\code\\retailer\\client\\src\\components\\ui\\A4PageView.jsx", "source_location": "L261", "weight": 1.0}, {"source": "d_code_retailer_client_src_components_ui_a4pageview_jsx", "target": "ui_a4pageview_a4pageview", "relation": "contains", "confidence": "EXTRACTED", "source_file": "D:\\code\\retailer\\client\\src\\components\\ui\\A4PageView.jsx", "source_location": "L277", "weight": 1.0}, {"source": "ui_a4pageview_a4pageview", "target": "ui_a4pageview_usecontainerscale", "relation": "calls", "context": "call", "confidence": "EXTRACTED", "source_file": "D:\\code\\retailer\\client\\src\\components\\ui\\A4PageView.jsx", "source_location": "L296", "weight": 1.0}], "raw_calls": [{"caller_nid": "ui_a4pageview_fmtdateeg", "callee": "isNaN", "is_member_call": true, "source_file": "D:\\code\\retailer\\client\\src\\components\\ui\\A4PageView.jsx", "source_location": "L6"}, {"caller_nid": "ui_a4pageview_fmtdateeg", "callee": "getTime", "is_member_call": true, "source_file": "D:\\code\\retailer\\client\\src\\components\\ui\\A4PageView.jsx", "source_location": "L6"}, {"caller_nid": "ui_a4pageview_fmtdateeg", "callee": "String", "is_member_call": false, "source_file": "D:\\code\\retailer\\client\\src\\components\\ui\\A4PageView.jsx", "source_location": "L6"}, {"caller_nid": "ui_a4pageview_fmtdateeg", "callee": "toLocaleDateString", "is_member_call": true, "source_file": "D:\\code\\retailer\\client\\src\\components\\ui\\A4PageView.jsx", "source_location": "L7"}, {"caller_nid": "ui_a4pageview_isnumericlike", "callee": "trim", "is_member_call": true, "source_file": "D:\\code\\retailer\\client\\src\\components\\ui\\A4PageView.jsx", "source_location": "L12"}, {"caller_nid": "ui_a4pageview_isnumericlike", "callee": "String", "is_member_call": false, "source_file": "D:\\code\\retailer\\client\\src\\components\\ui\\A4PageView.jsx", "source_location": "L12"}, {"caller_nid": "ui_a4pageview_isnumericlike", "callee": "isNaN", "is_member_call": true, "source_file": "D:\\code\\retailer\\client\\src\\components\\ui\\A4PageView.jsx", "source_location": "L14"}, {"caller_nid": "ui_a4pageview_isnumericlike", "callee": "Number", "is_member_call": false, "source_file": "D:\\code\\retailer\\client\\src\\components\\ui\\A4PageView.jsx", "source_location": "L14"}, {"caller_nid": "ui_a4pageview_a4sheet", "callee": "max", "is_member_call": true, "source_file": "D:\\code\\retailer\\client\\src\\components\\ui\\A4PageView.jsx", "source_location": "L43"}, {"caller_nid": "ui_a4pageview_a4sheet", "callee": "floor", "is_member_call": true, "source_file": "D:\\code\\retailer\\client\\src\\components\\ui\\A4PageView.jsx", "source_location": "L43"}, {"caller_nid": "ui_a4pageview_a4sheet", "callee": "slice", "is_member_call": true, "source_file": "D:\\code\\retailer\\client\\src\\components\\ui\\A4PageView.jsx", "source_location": "L44"}, {"caller_nid": "ui_a4pageview_a4sheet", "callee": "round", "is_member_call": true, "source_file": "D:\\code\\retailer\\client\\src\\components\\ui\\A4PageView.jsx", "source_location": "L48"}, {"caller_nid": "ui_a4pageview_a4sheet", "callee": "round", "is_member_call": true, "source_file": "D:\\code\\retailer\\client\\src\\components\\ui\\A4PageView.jsx", "source_location": "L49"}, {"caller_nid": "ui_a4pageview_a4sheet", "callee": "toLocaleDateString", "is_member_call": true, "source_file": "D:\\code\\retailer\\client\\src\\components\\ui\\A4PageView.jsx", "source_location": "L84"}, {"caller_nid": "ui_a4pageview_a4sheet", "callee": "toLocaleString", "is_member_call": true, "source_file": "D:\\code\\retailer\\client\\src\\components\\ui\\A4PageView.jsx", "source_location": "L86"}, {"caller_nid": "ui_a4pageview_a4sheet", "callee": "toLocaleString", "is_member_call": true, "source_file": "D:\\code\\retailer\\client\\src\\components\\ui\\A4PageView.jsx", "source_location": "L86"}, {"caller_nid": "ui_a4pageview_a4sheet", "callee": "map", "is_member_call": true, "source_file": "D:\\code\\retailer\\client\\src\\components\\ui\\A4PageView.jsx", "source_location": "L105"}, {"caller_nid": "ui_a4pageview_a4sheet", "callee": "map", "is_member_call": true, "source_file": "D:\\code\\retailer\\client\\src\\components\\ui\\A4PageView.jsx", "source_location": "L135"}, {"caller_nid": "ui_a4pageview_a4sheet", "callee": "keys", "is_member_call": true, "source_file": "D:\\code\\retailer\\client\\src\\components\\ui\\A4PageView.jsx", "source_location": "L183"}, {"caller_nid": "ui_a4pageview_a4sheet", "callee": "map", "is_member_call": true, "source_file": "D:\\code\\retailer\\client\\src\\components\\ui\\A4PageView.jsx", "source_location": "L196"}, {"caller_nid": "ui_a4pageview_a4sheet", "callee": "toLocaleDateString", "is_member_call": true, "source_file": "D:\\code\\retailer\\client\\src\\components\\ui\\A4PageView.jsx", "source_location": "L253"}, {"caller_nid": "ui_a4pageview_a4sheet", "callee": "toLocaleString", "is_member_call": true, "source_file": "D:\\code\\retailer\\client\\src\\components\\ui\\A4PageView.jsx", "source_location": "L254"}, {"caller_nid": "ui_a4pageview_a4sheet", "callee": "toLocaleString", "is_member_call": true, "source_file": "D:\\code\\retailer\\client\\src\\components\\ui\\A4PageView.jsx", "source_location": "L255"}, {"caller_nid": "ui_a4pageview_a4sheet", "callee": "toLocaleString", "is_member_call": true, "source_file": "D:\\code\\retailer\\client\\src\\components\\ui\\A4PageView.jsx", "source_location": "L255"}, {"caller_nid": "ui_a4pageview_usecontainerscale", "callee": "useState", "is_member_call": false, "source_file": "D:\\code\\retailer\\client\\src\\components\\ui\\A4PageView.jsx", "source_location": "L262"}, {"caller_nid": "ui_a4pageview_usecontainerscale", "callee": "useCallback", "is_member_call": false, "source_file": "D:\\code\\retailer\\client\\src\\components\\ui\\A4PageView.jsx", "source_location": "L263"}, {"caller_nid": "ui_a4pageview_usecontainerscale", "callee": "useEffect", "is_member_call": false, "source_file": "D:\\code\\retailer\\client\\src\\components\\ui\\A4PageView.jsx", "source_location": "L268"}, {"caller_nid": "ui_a4pageview_a4pageview", "callee": "useMemo", "is_member_call": false, "source_file": "D:\\code\\retailer\\client\\src\\components\\ui\\A4PageView.jsx", "source_location": "L290"}, {"caller_nid": "ui_a4pageview_a4pageview", "callee": "useRef", "is_member_call": false, "source_file": "D:\\code\\retailer\\client\\src\\components\\ui\\A4PageView.jsx", "source_location": "L295"}]}