{"nodes": [{"id": "d_code_retailer_server_src_services_returnservice_js", "label": "returnService.js", "file_type": "code", "source_file": "D:\\code\\retailer\\server\\src\\services\\returnService.js", "source_location": "L1"}, {"id": "services_returnservice_getdb", "label": "{ getDb }", "file_type": "code", "source_file": "D:\\code\\retailer\\server\\src\\services\\returnService.js", "source_location": "L1"}, {"id": "services_returnservice_adjuststock", "label": "{ adjustStock }", "file_type": "code", "source_file": "D:\\code\\retailer\\server\\src\\services\\returnService.js", "source_location": "L2"}, {"id": "services_returnservice_generatedocnumber", "label": "{ generateDocNumber }", "file_type": "code", "source_file": "D:\\code\\retailer\\server\\src\\services\\returnService.js", "source_location": "L3"}, {"id": "services_returnservice_assertcanwritefordate_normalizedate", "label": "{ assertCanWriteForDate, normalizeDate }", "file_type": "code", "source_file": "D:\\code\\retailer\\server\\src\\services\\returnService.js", "source_location": "L4"}, {"id": "services_returnservice_getsnapshotcosts", "label": "{ getSnapshotCosts }", "file_type": "code", "source_file": "D:\\code\\retailer\\server\\src\\services\\returnService.js", "source_location": "L5"}, {"id": "services_returnservice_generateamendmentdocno", "label": "generateAmendmentDocNo()", "file_type": "code", "source_file": "D:\\code\\retailer\\server\\src\\services\\returnService.js", "source_location": "L7"}, {"id": "services_returnservice_createreturn", "label": "createReturn()", "file_type": "code", "source_file": "D:\\code\\retailer\\server\\src\\services\\returnService.js", "source_location": "L17"}, {"id": "services_returnservice_creategeneralreturn", "label": "createGeneralReturn()", "file_type": "code", "source_file": "D:\\code\\retailer\\server\\src\\services\\returnService.js", "source_location": "L169"}, {"id": "services_returnservice_cancelsalesreturn", "label": "cancelSalesReturn()", "file_type": "code", "source_file": "D:\\code\\retailer\\server\\src\\services\\returnService.js", "source_location": "L214"}, {"id": "services_returnservice_amendsalesreturn", "label": "amendSalesReturn()", "file_type": "code", "source_file": "D:\\code\\retailer\\server\\src\\services\\returnService.js", "source_location": "L266"}, {"id": "services_returnservice_getreturns", "label": "getReturns()", "file_type": "code", "source_file": "D:\\code\\retailer\\server\\src\\services\\returnService.js", "source_location": "L311"}, {"id": "services_returnservice_getreturndetails", "label": "getReturnDetails()", "file_type": "code", "source_file": "D:\\code\\retailer\\server\\src\\services\\returnService.js", "source_location": "L322"}, {"id": "services_returnservice_editsalesreturn", "label": "editSalesReturn()", "file_type": "code", "source_file": "D:\\code\\retailer\\server\\src\\services\\returnService.js", "source_location": "L345"}], "edges": [{"source": "d_code_retailer_server_src_services_returnservice_js", "target": "d_code_retailer_server_src_config_database_js", "relation": "imports_from", "context": "import", "confidence": "EXTRACTED", "source_file": "D:\\code\\retailer\\server\\src\\services\\returnService.js", "source_location": "L1", "weight": 1.0}, {"source": "d_code_retailer_server_src_services_returnservice_js", "target": "config_database_getdb", "relation": "imports", "context": "import", "confidence": "EXTRACTED", "source_file": "D:\\code\\retailer\\server\\src\\services\\returnService.js", "source_location": "L1", "weight": 1.0}, {"source": "d_code_retailer_server_src_services_returnservice_js", "target": "services_returnservice_getdb", "relation": "contains", "confidence": "EXTRACTED", "source_file": "D:\\code\\retailer\\server\\src\\services\\returnService.js", "source_location": "L1", "weight": 1.0}, {"source": "d_code_retailer_server_src_services_returnservice_js", "target": "d_code_retailer_server_src_services_stockservice_js", "relation": "imports_from", "context": "import", "confidence": "EXTRACTED", "source_file": "D:\\code\\retailer\\server\\src\\services\\returnService.js", "source_location": "L2", "weight": 1.0}, {"source": "d_code_retailer_server_src_services_returnservice_js", "target": "services_stockservice_adjuststock", "relation": "imports", "context": "import", "confidence": "EXTRACTED", "source_file": "D:\\code\\retailer\\server\\src\\services\\returnService.js", "source_location": "L2", "weight": 1.0}, {"source": "d_code_retailer_server_src_services_returnservice_js", "target": "services_returnservice_adjuststock", "relation": "contains", "confidence": "EXTRACTED", "source_file": "D:\\code\\retailer\\server\\src\\services\\returnService.js", "source_location": "L2", "weight": 1.0}, {"source": "d_code_retailer_server_src_services_returnservice_js", "target": "d_code_retailer_server_src_utils_docnumber_js", "relation": "imports_from", "context": "import", "confidence": "EXTRACTED", "source_file": "D:\\code\\retailer\\server\\src\\services\\returnService.js", "source_location": "L3", "weight": 1.0}, {"source": "d_code_retailer_server_src_services_returnservice_js", "target": "utils_docnumber_generatedocnumber", "relation": "imports", "context": "import", "confidence": "EXTRACTED", "source_file": "D:\\code\\retailer\\server\\src\\services\\returnService.js", "source_location": "L3", "weight": 1.0}, {"source": "d_code_retailer_server_src_services_returnservice_js", "target": "services_returnservice_generatedocnumber", "relation": "contains", "confidence": "EXTRACTED", "source_file": "D:\\code\\retailer\\server\\src\\services\\returnService.js", "source_location": "L3", "weight": 1.0}, {"source": "d_code_retailer_server_src_services_returnservice_js", "target": "d_code_retailer_server_src_services_dailysessionservice_js", "relation": "imports_from", "context": "import", "confidence": "EXTRACTED", "source_file": "D:\\code\\retailer\\server\\src\\services\\returnService.js", "source_location": "L4", "weight": 1.0}, {"source": "d_code_retailer_server_src_services_returnservice_js", "target": "services_dailysessionservice_assertcanwritefordate", "relation": "imports", "context": "import", "confidence": "EXTRACTED", "source_file": "D:\\code\\retailer\\server\\src\\services\\returnService.js", "source_location": "L4", "weight": 1.0}, {"source": "d_code_retailer_server_src_services_returnservice_js", "target": "services_dailysessionservice_normalizedate", "relation": "imports", "context": "import", "confidence": "EXTRACTED", "source_file": "D:\\code\\retailer\\server\\src\\services\\returnService.js", "source_location": "L4", "weight": 1.0}, {"source": "d_code_retailer_server_src_services_returnservice_js", "target": "services_returnservice_assertcanwritefordate_normalizedate", "relation": "contains", "confidence": "EXTRACTED", "source_file": "D:\\code\\retailer\\server\\src\\services\\returnService.js", "source_location": "L4", "weight": 1.0}, {"source": "d_code_retailer_server_src_services_returnservice_js", "target": "d_code_retailer_server_src_services_waccservice_js", "relation": "imports_from", "context": "import", "confidence": "EXTRACTED", "source_file": "D:\\code\\retailer\\server\\src\\services\\returnService.js", "source_location": "L5", "weight": 1.0}, {"source": "d_code_retailer_server_src_services_returnservice_js", "target": "services_waccservice_getsnapshotcosts", "relation": "imports", "context": "import", "confidence": "EXTRACTED", "source_file": "D:\\code\\retailer\\server\\src\\services\\returnService.js", "source_location": "L5", "weight": 1.0}, {"source": "d_code_retailer_server_src_services_returnservice_js", "target": "services_returnservice_getsnapshotcosts", "relation": "contains", "confidence": "EXTRACTED", "source_file": "D:\\code\\retailer\\server\\src\\services\\returnService.js", "source_location": "L5", "weight": 1.0}, {"source": "d_code_retailer_server_src_services_returnservice_js", "target": "services_returnservice_generateamendmentdocno", "relation": "contains", "confidence": "EXTRACTED", "source_file": "D:\\code\\retailer\\server\\src\\services\\returnService.js", "source_location": "L7", "weight": 1.0}, {"source": "d_code_retailer_server_src_services_returnservice_js", "target": "services_returnservice_createreturn", "relation": "contains", "confidence": "EXTRACTED", "source_file": "D:\\code\\retailer\\server\\src\\services\\returnService.js", "source_location": "L17", "weight": 1.0}, {"source": "d_code_retailer_server_src_services_returnservice_js", "target": "services_returnservice_creategeneralreturn", "relation": "contains", "confidence": "EXTRACTED", "source_file": "D:\\code\\retailer\\server\\src\\services\\returnService.js", "source_location": "L169", "weight": 1.0}, {"source": "d_code_retailer_server_src_services_returnservice_js", "target": "services_returnservice_cancelsalesreturn", "relation": "contains", "confidence": "EXTRACTED", "source_file": "D:\\code\\retailer\\server\\src\\services\\returnService.js", "source_location": "L214", "weight": 1.0}, {"source": "d_code_retailer_server_src_services_returnservice_js", "target": "services_returnservice_amendsalesreturn", "relation": "contains", "confidence": "EXTRACTED", "source_file": "D:\\code\\retailer\\server\\src\\services\\returnService.js", "source_location": "L266", "weight": 1.0}, {"source": "d_code_retailer_server_src_services_returnservice_js", "target": "services_returnservice_getreturns", "relation": "contains", "confidence": "EXTRACTED", "source_file": "D:\\code\\retailer\\server\\src\\services\\returnService.js", "source_location": "L311", "weight": 1.0}, {"source": "d_code_retailer_server_src_services_returnservice_js", "target": "services_returnservice_getreturndetails", "relation": "contains", "confidence": "EXTRACTED", "source_file": "D:\\code\\retailer\\server\\src\\services\\returnService.js", "source_location": "L322", "weight": 1.0}, {"source": "d_code_retailer_server_src_services_returnservice_js", "target": "services_returnservice_editsalesreturn", "relation": "contains", "confidence": "EXTRACTED", "source_file": "D:\\code\\retailer\\server\\src\\services\\returnService.js", "source_location": "L345", "weight": 1.0}], "raw_calls": [{"caller_nid": "services_returnservice_generateamendmentdocno", "callee": "replace", "is_member_call": true, "source_file": "D:\\code\\retailer\\server\\src\\services\\returnService.js", "source_location": "L8"}, {"caller_nid": "services_returnservice_generateamendmentdocno", "callee": "get", "is_member_call": true, "source_file": "D:\\code\\retailer\\server\\src\\services\\returnService.js", "source_location": "L9"}, {"caller_nid": "services_returnservice_generateamendmentdocno", "callee": "prepare", "is_member_call": true, "source_file": "D:\\code\\retailer\\server\\src\\services\\returnService.js", "source_location": "L9"}, {"caller_nid": "services_returnservice_generateamendmentdocno", "callee": "parseInt", "is_member_call": false, "source_file": "D:\\code\\retailer\\server\\src\\services\\returnService.js", "source_location": "L13"}, {"caller_nid": "services_returnservice_generateamendmentdocno", "callee": "match", "is_member_call": true, "source_file": "D:\\code\\retailer\\server\\src\\services\\returnService.js", "source_location": "L13"}, {"caller_nid": "services_returnservice_createreturn", "callee": "getDb", "is_member_call": false, "source_file": "D:\\code\\retailer\\server\\src\\services\\returnService.js", "source_location": "L18"}, {"caller_nid": "services_returnservice_createreturn", "callee": "db.transaction(() => {\r\n    const createdDate = normalizeDate(payload.created_at);\r\n    assertCanWriteForDate(db, createdDate);\r\n    const invoice = db.prepare(\"SELECT * FROM invoices WHERE id = ?\").get(invoiceId);\r\n    if (!invoice) {\r\n      const err = new Error(\"Invoice not found\");\r\n      err.status = 404;\r\n      throw err;\r\n    }\r\n\r\n    let total = 0;\r\n    const preparedLines = [];\r\n\r\n    for (const requestedLine of payload.lines || []) {\r\n      const invoiceLine = db\r\n        .prepare(\"SELECT * FROM invoice_lines WHERE id = ? AND invoice_id = ?\")\r\n        .get(requestedLine.invoice_line_id, invoiceId);\r\n\r\n      if (!invoiceLine) {\r\n        const err = new Error(\"Invoice line not found\");\r\n        err.status = 404;\r\n        throw err;\r\n      }\r\n\r\n      const previousReturned =\r\n        db\r\n          .prepare(\r\n            \"SELECT COALESCE(SUM(quantity), 0) AS quantity FROM sales_return_lines WHERE invoice_line_id = ? AND sales_return_id IN (SELECT id FROM sales_returns WHERE status != 'cancelled')\",\r\n          )\r\n          .get(invoiceLine.id).quantity || 0;\r\n\r\n      const remaining = invoiceLine.quantity - previousReturned;\r\n      if (requestedLine.quantity <= 0 || requestedLine.quantity > remaining) {\r\n        const err = new Error(\"Invalid return quantity\");\r\n        err.status = 400;\r\n        throw err;\r\n      }\r\n\r\n      const lineTotal = invoiceLine.unit_price * requestedLine.quantity;\r\n      total += lineTotal;\r\n\r\n      // Snapshot costs + names\r\n      const itemRow = db.prepare(\"SELECT name, name_en FROM items WHERE id = ?\").get(invoiceLine.item_id);\r\n      const snap = getSnapshotCosts(invoiceLine.item_id, db);\r\n      preparedLines.push({\r\n        invoice_line_id: invoiceLine.id,\r\n        item_id: invoiceLine.item_id,\r\n        quantity: requestedLine.quantity,\r\n        unit_price: invoiceLine.unit_price,\r\n        line_total: lineTotal,\r\n        // warehouse from original invoice line (Option A)\r\n        warehouse_id: invoiceLine.warehouse_id || 1,\r\n        item_name_ar: itemRow?.name    || invoiceLine.item_name_ar || null,\r\n        item_name_en: itemRow?.name_en || invoiceLine.item_name_en || null,\r\n        cost_wacc:          snap.cost_wacc,\r\n        cost_last_purchase: snap.cost_last_purchase,\r\n      });\r\n    }\r\n\r\n    const docNo = generateDocNumber('sales_return');\r\n    const result = db\r\n      .prepare(\r\n        \"INSERT INTO sales_returns (doc_no, invoice_id, customer_id, total, reason, refund_method, notes, status, created_by, created_at) VALUES (?, ?, ?, ?, ?, ?, ?, 'active', ?, ?)\",\r\n      )\r\n      .run(\r\n        docNo,\r\n        invoiceId,\r\n        invoice.customer_id || null,\r\n        total,\r\n        payload.reason || null,\r\n        payload.refund_method || \"cash_back\",\r\n        payload.notes || null,\r\n        payload.user_id || null,\r\n        `${createdDate} ${new Date().toTimeString().slice(0, 8)}`,\r\n      );\r\n\r\n    const returnId = result.lastInsertRowid;\r\n\r\n    for (const line of preparedLines) {\r\n      db.prepare(\r\n        `INSERT INTO sales_return_lines\r\n          (sales_return_id, invoice_line_id, item_id, quantity, unit_price, line_total,\r\n           warehouse_id, item_name_ar, item_name_en, cost_wacc, cost_last_purchase)\r\n         VALUES (?, ?, ?, ?, ?, ?, ?, ?, ?, ?, ?)`,\r\n      ).run(returnId, line.invoice_line_id, line.item_id, line.quantity,\r\n            line.unit_price, line.line_total, line.warehouse_id,\r\n            line.item_name_ar, line.item_name_en, line.cost_wacc, line.cost_last_purchase);\r\n\r\n      adjustStock({\r\n        item_id: line.item_id,\r\n        warehouse_id: line.warehouse_id,\r\n        quantityDelta: line.quantity,\r\n        movement_type: \"sales_return\",\r\n        reference_type: \"sales_return\",\r\n        reference_id: returnId,\r\n      });\r\n    }\r\n\r\n    if (invoice.customer_id && (invoice.payment_type === \"credit\" || payload.refund_method === \"credit_note\")) {\r\n      db.prepare(\"UPDATE customers SET opening_balance = opening_balance - ? WHERE id = ?\").run(\r\n        total, invoice.customer_id,\r\n      );\r\n      db.prepare(\"UPDATE ajal_debts SET original_amount = original_amount - ? WHERE invoice_id = ? AND status = 'open'\").run(\r\n        total, invoiceId,\r\n      );\r\n    } else if (invoice.payment_type === \"bank_transfer\" && invoice.bank_id) {\r\n      db.prepare(\"UPDATE banks SET balance = balance - ? WHERE id = ?\").run(total, invoice.bank_id);\r\n    } else if (invoice.payment_type === \"multi\") {\r\n      const allocations = db.prepare(`\r\n        SELECT pa.amount, p.method, p.treasury_id, p.bank_id\r\n        FROM payment_allocations pa\r\n        LEFT JOIN payments p ON p.id = pa.payment_id\r\n        WHERE pa.invoice_id = ?\r\n      `).all(invoiceId);\r\n      const invoiceTotal = Number(invoice.total) || 1;\r\n      for (const alloc of allocations) {\r\n        const portion = (Number(alloc.amount) / invoiceTotal) * total;\r\n        if (alloc.method === \"cash\" && alloc.treasury_id) {\r\n          db.prepare(\"UPDATE treasuries SET balance = balance - ? WHERE id = ?\").run(portion, alloc.treasury_id);\r\n        } else if (alloc.method === \"bank\" && alloc.bank_id) {\r\n          db.prepare(\"UPDATE banks SET balance = balance - ? WHERE id = ?\").run(portion, alloc.bank_id);\r\n        }\r\n      }\r\n    } else if (invoice.payment_type === \"cash\" || payload.refund_method === \"cash_back\") {\r\n      const treasuryId =\r\n        payload.treasury_id ||\r\n        db.prepare(\"SELECT default_treasury_id FROM settings WHERE id = 1\").get()?.default_treasury_id;\r\n      if (treasuryId) {\r\n        db.prepare(\"UPDATE treasuries SET balance = balance - ? WHERE id = ?\").run(total, treasuryId);\r\n      }\r\n    }\r\n\r\n    const invoiceLines = db.prepare(\"SELECT id, quantity FROM invoice_lines WHERE invoice_id = ?\").all(invoiceId);\r\n    const fullyReturned = invoiceLines.every((line) => {\r\n      const returnedQty =\r\n        db.prepare(\r\n          \"SELECT COALESCE(SUM(srl.quantity), 0) AS quantity FROM sales_return_lines srl JOIN sales_returns sr ON sr.id = srl.sales_return_id WHERE srl.invoice_line_id = ? AND sr.status != 'cancelled'\"\r\n        ).get(line.id).quantity || 0;\r\n      return returnedQty >= line.quantity;\r\n    });\r\n    db.prepare(\"UPDATE invoices SET status = ? WHERE id = ?\").run(\r\n      fullyReturned ? \"returned\" : \"partially_returned\",\r\n      invoiceId,\r\n    );\r\n\r\n    return db.prepare(\"SELECT * FROM sales_returns WHERE id = ?\").get(returnId);\r\n  })", "is_member_call": false, "source_file": "D:\\code\\retailer\\server\\src\\services\\returnService.js", "source_location": "L20"}, {"caller_nid": "services_returnservice_createreturn", "callee": "transaction", "is_member_call": true, "source_file": "D:\\code\\retailer\\server\\src\\services\\returnService.js", "source_location": "L20"}, {"caller_nid": "services_returnservice_creategeneralreturn", "callee": "getDb", "is_member_call": false, "source_file": "D:\\code\\retailer\\server\\src\\services\\returnService.js", "source_location": "L170"}, {"caller_nid": "services_returnservice_creategeneralreturn", "callee": "db.transaction(() => {\r\n    const { lines, customer_id, refund_method, notes, reason, user_id, treasury_id } = payload;\r\n    if (!lines || !lines.length) { const e = new Error(\"\u064a\u062c\u0628 \u0625\u0636\u0627\u0641\u0629 \u0623\u0635\u0646\u0627\u0641\"); e.status = 400; throw e; }\r\n\r\n    const docNo = generateDocNumber('sales_return');\r\n    let total = 0;\r\n    for (const line of lines) total += Number(line.quantity) * Number(line.unit_price);\r\n\r\n    const ret = db.prepare(\r\n      \"INSERT INTO sales_returns (doc_no, invoice_id, customer_id, total, refund_method, reason, notes, status, created_by, created_at) VALUES (?, NULL, ?, ?, ?, ?, ?, 'active', ?, datetime('now', 'localtime'))\"\r\n    ).run(docNo, customer_id || null, total, refund_method || 'cash_back', reason || 'other', notes || null, user_id || null);\r\n\r\n    const returnId = ret.lastInsertRowid;\r\n\r\n    for (const line of lines) {\r\n      const lineTotal = Number(line.quantity) * Number(line.unit_price);\r\n      const itemRow = db.prepare(\"SELECT name, name_en FROM items WHERE id = ?\").get(line.item_id);\r\n      const snap = getSnapshotCosts(line.item_id, db);\r\n      const warehouseId = Number(line.warehouse_id || 1);\r\n\r\n      db.prepare(\r\n        `INSERT INTO sales_return_lines\r\n          (sales_return_id, invoice_line_id, item_id, quantity, unit_price, line_total,\r\n           warehouse_id, item_name_ar, item_name_en, cost_wacc, cost_last_purchase)\r\n         VALUES (?, NULL, ?, ?, ?, ?, ?, ?, ?, ?, ?)`\r\n      ).run(returnId, line.item_id, line.quantity, line.unit_price, lineTotal,\r\n            warehouseId, itemRow?.name || null, itemRow?.name_en || null,\r\n            snap.cost_wacc, snap.cost_last_purchase);\r\n\r\n      adjustStock({ item_id: line.item_id, warehouse_id: warehouseId, quantityDelta: Number(line.quantity), movement_type: \"sales_return\", reference_type: \"sales_return\", reference_id: returnId });\r\n    }\r\n\r\n    if (refund_method === 'cash_back' || !refund_method) {\r\n      const tId = treasury_id || db.prepare(\"SELECT default_treasury_id FROM settings WHERE id = 1\").get()?.default_treasury_id;\r\n      if (tId) db.prepare(\"UPDATE treasuries SET balance = balance - ? WHERE id = ?\").run(total, tId);\r\n    } else if (refund_method === 'credit_note' && customer_id) {\r\n      db.prepare(\"UPDATE customers SET opening_balance = opening_balance - ? WHERE id = ?\").run(total, customer_id);\r\n    }\r\n\r\n    return { id: returnId, doc_no: docNo, total };\r\n  })", "is_member_call": false, "source_file": "D:\\code\\retailer\\server\\src\\services\\returnService.js", "source_location": "L171"}, {"caller_nid": "services_returnservice_creategeneralreturn", "callee": "transaction", "is_member_call": true, "source_file": "D:\\code\\retailer\\server\\src\\services\\returnService.js", "source_location": "L171"}, {"caller_nid": "services_returnservice_cancelsalesreturn", "callee": "trim", "is_member_call": true, "source_file": "D:\\code\\retailer\\server\\src\\services\\returnService.js", "source_location": "L215"}, {"caller_nid": "services_returnservice_cancelsalesreturn", "callee": "getDb", "is_member_call": false, "source_file": "D:\\code\\retailer\\server\\src\\services\\returnService.js", "source_location": "L216"}, {"caller_nid": "services_returnservice_cancelsalesreturn", "callee": "db.transaction(() => {\r\n    const sr = db.prepare(\"SELECT * FROM sales_returns WHERE id = ?\").get(returnId);\r\n    if (!sr) { const e = new Error(\"\u0627\u0644\u0645\u0631\u062a\u062c\u0639 \u063a\u064a\u0631 \u0645\u0648\u062c\u0648\u062f\"); e.status = 404; throw e; }\r\n    if (sr.status === 'cancelled') { const e = new Error(\"\u0627\u0644\u0645\u0631\u062a\u062c\u0639 \u0645\u0644\u063a\u0649 \u0628\u0627\u0644\u0641\u0639\u0644\"); e.status = 400; throw e; }\r\n    if (sr.amended_by) { const e = new Error(\"\u0647\u0630\u0627 \u0627\u0644\u0645\u0631\u062a\u062c\u0639 \u0639\u064f\u062f\u0650\u0651\u0644 \u0628\u0627\u0644\u0641\u0639\u0644\"); e.status = 400; throw e; }\r\n\r\n    const lines = db.prepare(\"SELECT * FROM sales_return_lines WHERE sales_return_id = ?\").all(returnId);\r\n\r\n    // Reverse stock (remove what was added back)\r\n    for (const line of lines) {\r\n      adjustStock({\r\n        item_id: line.item_id,\r\n        warehouse_id: line.warehouse_id || 1,\r\n        quantityDelta: -line.quantity,\r\n        movement_type: \"cancel_sales_return\",\r\n        reference_type: \"sales_return\",\r\n        reference_id: returnId,\r\n      });\r\n    }\r\n\r\n    // Reverse financials\r\n    const refundMethod = sr.refund_method;\r\n    if (refundMethod === 'cash_back') {\r\n      const tId = db.prepare(\"SELECT default_treasury_id FROM settings WHERE id = 1\").get()?.default_treasury_id;\r\n      if (tId) db.prepare(\"UPDATE treasuries SET balance = balance + ? WHERE id = ?\").run(sr.total, tId);\r\n    } else if (refundMethod === 'credit_note' && sr.customer_id) {\r\n      db.prepare(\"UPDATE customers SET opening_balance = opening_balance + ? WHERE id = ?\").run(sr.total, sr.customer_id);\r\n    }\r\n\r\n    const now = new Date().toISOString().replace(\"T\", \" \").slice(0, 19);\r\n    db.prepare(\"UPDATE sales_returns SET status = 'cancelled', cancelled_at = ?, cancelled_by = ?, cancel_reason = ? WHERE id = ?\")\r\n      .run(now, userId || null, reason.trim(), returnId);\r\n\r\n    // Recalculate original invoice status if linked\r\n    if (sr.invoice_id) {\r\n      const { recalculateInvoiceStatus } = require(\"./invoiceService\");\r\n      try { recalculateInvoiceStatus(db, sr.invoice_id); } catch (_) {}\r\n    }\r\n\r\n    try {\r\n      db.prepare(\"INSERT INTO audit_logs (user_id, resource, resource_id, action, details) VALUES (?, ?, ?, ?, ?)\").run(\r\n        userId || 1, \"sales_return\", returnId, \"cancel\", JSON.stringify({ reason })\r\n      );\r\n    } catch (_) {}\r\n\r\n    return db.prepare(\"SELECT * FROM sales_returns WHERE id = ?\").get(returnId);\r\n  })", "is_member_call": false, "source_file": "D:\\code\\retailer\\server\\src\\services\\returnService.js", "source_location": "L217"}, {"caller_nid": "services_returnservice_cancelsalesreturn", "callee": "transaction", "is_member_call": true, "source_file": "D:\\code\\retailer\\server\\src\\services\\returnService.js", "source_location": "L217"}, {"caller_nid": "services_returnservice_amendsalesreturn", "callee": "trim", "is_member_call": true, "source_file": "D:\\code\\retailer\\server\\src\\services\\returnService.js", "source_location": "L267"}, {"caller_nid": "services_returnservice_amendsalesreturn", "callee": "getDb", "is_member_call": false, "source_file": "D:\\code\\retailer\\server\\src\\services\\returnService.js", "source_location": "L268"}, {"caller_nid": "services_returnservice_amendsalesreturn", "callee": "get", "is_member_call": true, "source_file": "D:\\code\\retailer\\server\\src\\services\\returnService.js", "source_location": "L270"}, {"caller_nid": "services_returnservice_amendsalesreturn", "callee": "prepare", "is_member_call": true, "source_file": "D:\\code\\retailer\\server\\src\\services\\returnService.js", "source_location": "L270"}, {"caller_nid": "services_returnservice_amendsalesreturn", "callee": "db.transaction(() => {\r\n  // Cancel original\r\n  cancelSalesReturn(returnId, `\u062a\u0639\u062f\u064a\u0644 \u2014 ${payload.reason.trim()}`, userId);\r\n\r\n  // Create new return\r\n  const newPayload = { ...payload, user_id: userId };\r\n  delete newPayload.reason;\r\n\r\n  let newReturn;\r\n  if (original.invoice_id && !payload.is_general) {\r\n    newReturn = createReturn(original.invoice_id, newPayload);\r\n  } else {\r\n    newReturn = createGeneralReturn(newPayload);\r\n  }\r\n\r\n  // Override doc_no with amendment suffix\r\n  const newDocNo = generateAmendmentDocNo(original.doc_no, db, \"sales_returns\");\r\n  db.prepare(\"UPDATE sales_returns SET doc_no = ?, amendment_of = ? WHERE id = ?\")\r\n    .run(newDocNo, original.id, newReturn.id);\r\n\r\n  // Link original \u2192 new\r\n  db.prepare(\"UPDATE sales_returns SET amended_by = ? WHERE id = ?\").run(newReturn.id, original.id);\r\n\r\n  try {\r\n    db.prepare(\"INSERT INTO audit_logs (user_id, resource, resource_id, action, details) VALUES (?, ?, ?, ?, ?)\").run(\r\n      userId || 1, \"sales_return\", original.id, \"amend\", JSON.stringify({ new_return_id: newReturn.id, reason: payload.reason })\r\n    );\r\n  } catch (_) {}\r\n\r\n  return {\r\n    original: db.prepare(\"SELECT * FROM sales_returns WHERE id = ?\").get(original.id),\r\n    new_return: db.prepare(\"SELECT * FROM sales_returns WHERE id = ?\").get(newReturn.id),\r\n  };\r\n  })", "is_member_call": false, "source_file": "D:\\code\\retailer\\server\\src\\services\\returnService.js", "source_location": "L275"}, {"caller_nid": "services_returnservice_amendsalesreturn", "callee": "transaction", "is_member_call": true, "source_file": "D:\\code\\retailer\\server\\src\\services\\returnService.js", "source_location": "L275"}, {"caller_nid": "services_returnservice_getreturns", "callee": "getDb", "is_member_call": false, "source_file": "D:\\code\\retailer\\server\\src\\services\\returnService.js", "source_location": "L312"}, {"caller_nid": "services_returnservice_getreturns", "callee": "all", "is_member_call": true, "source_file": "D:\\code\\retailer\\server\\src\\services\\returnService.js", "source_location": "L313"}, {"caller_nid": "services_returnservice_getreturns", "callee": "prepare", "is_member_call": true, "source_file": "D:\\code\\retailer\\server\\src\\services\\returnService.js", "source_location": "L313"}, {"caller_nid": "services_returnservice_getreturndetails", "callee": "getDb", "is_member_call": false, "source_file": "D:\\code\\retailer\\server\\src\\services\\returnService.js", "source_location": "L323"}, {"caller_nid": "services_returnservice_getreturndetails", "callee": "get", "is_member_call": true, "source_file": "D:\\code\\retailer\\server\\src\\services\\returnService.js", "source_location": "L324"}, {"caller_nid": "services_returnservice_getreturndetails", "callee": "prepare", "is_member_call": true, "source_file": "D:\\code\\retailer\\server\\src\\services\\returnService.js", "source_location": "L324"}, {"caller_nid": "services_returnservice_getreturndetails", "callee": "all", "is_member_call": true, "source_file": "D:\\code\\retailer\\server\\src\\services\\returnService.js", "source_location": "L336"}, {"caller_nid": "services_returnservice_getreturndetails", "callee": "prepare", "is_member_call": true, "source_file": "D:\\code\\retailer\\server\\src\\services\\returnService.js", "source_location": "L336"}, {"caller_nid": "services_returnservice_editsalesreturn", "callee": "getDb", "is_member_call": false, "source_file": "D:\\code\\retailer\\server\\src\\services\\returnService.js", "source_location": "L346"}, {"caller_nid": "services_returnservice_editsalesreturn", "callee": "db.transaction(() => {\r\n    const sr = db.prepare(\"SELECT * FROM sales_returns WHERE id = ?\").get(returnId);\r\n    if (!sr) { const e = new Error(\"\u0627\u0644\u0645\u0631\u062a\u062c\u0639 \u063a\u064a\u0631 \u0645\u0648\u062c\u0648\u062f\"); e.status = 404; throw e; }\r\n    if (sr.status === \"cancelled\") { const e = new Error(\"\u0644\u0627 \u064a\u0645\u0643\u0646 \u062a\u0639\u062f\u064a\u0644 \u0645\u0631\u062a\u062c\u0639 \u0645\u0644\u063a\u0649\"); e.status = 400; throw e; }\r\n\r\n    const oldLines = db.prepare(\"SELECT * FROM sales_return_lines WHERE sales_return_id = ?\").all(returnId);\r\n\r\n    // 1. Reverse old stock\r\n    for (const line of oldLines) {\r\n      adjustStock({ item_id: line.item_id, warehouse_id: line.warehouse_id || 1, quantityDelta: -line.quantity, movement_type: \"cancel_sales_return\", reference_type: \"sales_return\", reference_id: returnId });\r\n    }\r\n\r\n    // 2. Reverse old financials\r\n    if (sr.refund_method === \"cash_back\") {\r\n      const tId = sr.treasury_id || db.prepare(\"SELECT default_treasury_id FROM settings WHERE id = 1\").get()?.default_treasury_id;\r\n      if (tId) db.prepare(\"UPDATE treasuries SET balance = balance + ? WHERE id = ?\").run(sr.total, tId);\r\n    } else if (sr.refund_method === \"credit_note\" && sr.customer_id) {\r\n      db.prepare(\"UPDATE customers SET opening_balance = opening_balance + ? WHERE id = ?\").run(sr.total, sr.customer_id);\r\n    }\r\n\r\n    // 3. Build new lines\r\n    const newLines = payload.lines || [];\r\n    let newTotal = 0;\r\n    const preparedLines = [];\r\n\r\n    for (const requestedLine of newLines) {\r\n      if (!sr.invoice_id) {\r\n        const itemRow = db.prepare(\"SELECT name, name_en FROM items WHERE id = ?\").get(requestedLine.item_id);\r\n        const snap = getSnapshotCosts(requestedLine.item_id, db);\r\n        const lineTotal = Number(requestedLine.quantity) * Number(requestedLine.unit_price);\r\n        newTotal += lineTotal;\r\n        preparedLines.push({ invoice_line_id: null, item_id: requestedLine.item_id, quantity: Number(requestedLine.quantity), unit_price: Number(requestedLine.unit_price), line_total: lineTotal, warehouse_id: payload.warehouse_id || 1, item_name_ar: itemRow?.name || null, item_name_en: itemRow?.name_en || null, cost_wacc: snap.cost_wacc, cost_last_purchase: snap.cost_last_purchase });\r\n      } else {\r\n        const invoiceLine = db.prepare(\"SELECT * FROM invoice_lines WHERE id = ? AND invoice_id = ?\").get(requestedLine.invoice_line_id, sr.invoice_id);\r\n        if (!invoiceLine) continue;\r\n        const previousReturned = db.prepare(\r\n          \"SELECT COALESCE(SUM(srl.quantity), 0) AS quantity FROM sales_return_lines srl JOIN sales_returns sr2 ON sr2.id = srl.sales_return_id WHERE srl.invoice_line_id = ? AND sr2.status != 'cancelled' AND sr2.id != ?\"\r\n        ).get(invoiceLine.id, returnId).quantity || 0;\r\n        const remaining = invoiceLine.quantity - previousReturned;\r\n        const qty = Math.min(Number(requestedLine.quantity), remaining);\r\n        if (qty <= 0) continue;\r\n        const lineTotal = invoiceLine.unit_price * qty;\r\n        newTotal += lineTotal;\r\n        preparedLines.push({ invoice_line_id: invoiceLine.id, item_id: invoiceLine.item_id, quantity: qty, unit_price: invoiceLine.unit_price, line_total: lineTotal, warehouse_id: payload.warehouse_id || invoiceLine.warehouse_id || 1, item_name_ar: invoiceLine.item_name_ar, item_name_en: invoiceLine.item_name_en, cost_wacc: invoiceLine.cost_wacc, cost_last_purchase: invoiceLine.cost_last_purchase });\r\n      }\r\n    }\r\n\r\n    // 4. Delete old lines, insert new\r\n    db.prepare(\"DELETE FROM sales_return_lines WHERE sales_return_id = ?\").run(returnId);\r\n    for (const line of preparedLines) {\r\n      db.prepare(\r\n        `INSERT INTO sales_return_lines (sales_return_id, invoice_line_id, item_id, quantity, unit_price, line_total, warehouse_id, item_name_ar, item_name_en, cost_wacc, cost_last_purchase)\r\n         VALUES (?, ?, ?, ?, ?, ?, ?, ?, ?, ?, ?)`\r\n      ).run(returnId, line.invoice_line_id, line.item_id, line.quantity, line.unit_price, line.line_total, line.warehouse_id, line.item_name_ar, line.item_name_en, line.cost_wacc || 0, line.cost_last_purchase || 0);\r\n      adjustStock({ item_id: line.item_id, warehouse_id: line.warehouse_id, quantityDelta: line.quantity, movement_type: \"sales_return\", reference_type: \"sales_return\", reference_id: returnId });\r\n    }\r\n\r\n    // 5. Apply new financials\r\n    const newRefundMethod = payload.refund_method || sr.refund_method;\r\n    const newTreasuryId = payload.treasury_id || sr.treasury_id;\r\n    const newCustomerId = payload.customer_id || sr.customer_id;\r\n    if (newRefundMethod === \"cash_back\") {\r\n      const tId = newTreasuryId || db.prepare(\"SELECT default_treasury_id FROM settings WHERE id = 1\").get()?.default_treasury_id;\r\n      if (tId) db.prepare(\"UPDATE treasuries SET balance = balance - ? WHERE id = ?\").run(newTotal, tId);\r\n    } else if (newRefundMethod === \"credit_note\" && newCustomerId) {\r\n      db.prepare(\"UPDATE customers SET opening_balance = opening_balance - ? WHERE id = ?\").run(newTotal, newCustomerId);\r\n    }\r\n\r\n    // 6. Update header \u2014 preserve doc_no and created_at\r\n    db.prepare(\r\n      \"UPDATE sales_returns SET total = ?, refund_method = ?, warehouse_id = ?, customer_id = ?, reason = ?, notes = ?, treasury_id = ? WHERE id = ?\"\r\n    ).run(newTotal, newRefundMethod, payload.warehouse_id || sr.warehouse_id, newCustomerId, payload.reason || sr.reason, payload.notes || sr.notes, newTreasuryId || null, returnId);\r\n\r\n    // 7. Recalculate linked invoice status\r\n    if (sr.invoice_id) {\r\n      const { recalculateInvoiceStatus } = require(\"./invoiceService\");\r\n      try { recalculateInvoiceStatus(db, sr.invoice_id); } catch (_) {}\r\n    }\r\n\r\n    try {\r\n      db.prepare(\"INSERT INTO audit_logs (user_id, resource, resource_id, action, details) VALUES (?, ?, ?, ?, ?)\").run(userId || 1, \"sales_return\", returnId, \"edit\", JSON.stringify({ lines_count: preparedLines.length, total: newTotal }));\r\n    } catch (_) {}\r\n\r\n    return getReturnDetails(returnId);\r\n  })", "is_member_call": false, "source_file": "D:\\code\\retailer\\server\\src\\services\\returnService.js", "source_location": "L347"}, {"caller_nid": "services_returnservice_editsalesreturn", "callee": "transaction", "is_member_call": true, "source_file": "D:\\code\\retailer\\server\\src\\services\\returnService.js", "source_location": "L347"}]}